{
  "controllerId": "mysticfactory1",
  "name": "Mystical Factory Tier 1",
  "textureOverride": "mysticalagriculture:block/prosperity_gemstone_block",
  "ports": [
    {
      "type": "masterfulmachinery:items",
      "textureOverride": "mysticalagriculture:block/prosperity_gemstone_block",
      "name": "Item",
      "id": "mystical_item",
      "data": {
        "rows": 3,
        "columns": 3
      }
    },
    {
      "type": "masterfulmachinery:energy",
      "textureOverride": "mysticalagriculture:block/prosperity_gemstone_block",
      "name": "Energy",
      "id": "mystical_energy",
      "data": {
        "capacity": 1000000
      }
    }
  ]
}
